bohrium_open_sdk/__init__.py
bohrium_open_sdk/_utils/__init__.py
bohrium_open_sdk/_utils/_logs.py
bohrium_open_sdk/_utils/_tools.py
bohrium_open_sdk/_utils/_typing.py
bohrium_open_sdk/_utils/_utils.py
bohrium_open_sdk/launching/__init__.py
bohrium_open_sdk/launching/compat.py
bohrium_open_sdk/launching/cli/__init__.py
bohrium_open_sdk/launching/cli/api/__init__.py
bohrium_open_sdk/launching/cli/api/model.py
bohrium_open_sdk/launching/cli/api/persistent_service.py
bohrium_open_sdk/launching/cli/commands/__init__.py
bohrium_open_sdk/launching/cli/commands/launching.py
bohrium_open_sdk/launching/cli/utils/__init__.py
bohrium_open_sdk/launching/cli/utils/random.py
bohrium_open_sdk/launching/report/__init__.py
bohrium_open_sdk/launching/typing/__init__.py
bohrium_open_sdk/launching/typing/basic.py
bohrium_open_sdk/launching/typing/benchmark.py
bohrium_open_sdk/launching/typing/bio.py
bohrium_open_sdk/launching/typing/bohrium.py
bohrium_open_sdk/launching/typing/dataset.py
bohrium_open_sdk/launching/typing/dflow.py
bohrium_open_sdk/launching/typing/io.py
bohrium_open_sdk/launching/typing/addon/__init__.py
bohrium_open_sdk/launching/typing/addon/sysmbol.py
bohrium_open_sdk/launching/typing/addon/ui.py
bohrium_open_sdk/opensdk/__init__.py
bohrium_open_sdk/opensdk/_base_client.py
bohrium_open_sdk/opensdk/_client.py
bohrium_open_sdk/opensdk/_constants.py
bohrium_open_sdk/opensdk/_exceptions.py
bohrium_open_sdk/opensdk/_resource.py
bohrium_open_sdk/opensdk/_response.py
bohrium_open_sdk/opensdk/_tiefblue_client.py
bohrium_open_sdk/opensdk/_types.py
bohrium_open_sdk/opensdk/_version.py
bohrium_open_sdk/opensdk/resources/__init__.py
bohrium_open_sdk/opensdk/resources/app/__init__.py
bohrium_open_sdk/opensdk/resources/app/app.py
bohrium_open_sdk/opensdk/resources/app/app_job.py
bohrium_open_sdk/opensdk/resources/app/stock.py
bohrium_open_sdk/opensdk/resources/app/web.py
bohrium_open_sdk/opensdk/resources/app/web_sub_model.py
bohrium_open_sdk/opensdk/resources/job/__init__.py
bohrium_open_sdk-0.1.0.dist-info/METADATA
bohrium_open_sdk-0.1.0.dist-info/WHEEL
bohrium_open_sdk-0.1.0.dist-info/top_level.txt
bohrium_open_sdk-0.1.0.dist-info/RECORD
