Metadata-Version: 2.1
Name: bohrium-open-sdk
Version: 0.1.0
Summary: bohrium-open-sdk
Home-page: https://bohrium.dp.tech/developer
Author: Bohrium Team
Requires-Python: >=3.8
Requires-Dist: httpx ==0.27.0
Requires-Dist: requests ==2.32.3
Requires-Dist: tqdm ==4.66.4
Requires-Dist: distro ==1.9.0
Requires-Dist: python-dotenv ==1.0.0
Requires-Dist: glom ==23.5.0
Requires-Dist: pytest ==8.2.2
Requires-Dist: gradio-materialviewer
Requires-Dist: gradio-mapping
Requires-Dist: gradio-perturbation-graph
Requires-Dist: gradio-fep-result-table
Requires-Dist: gradio-fep-pair-table
Requires-Dist: gradio-dp-project
Requires-Dist: gradio-dp-machine
Requires-Dist: dp-sequence-editor
Requires-Dist: gradio-uni-view
Requires-Dist: gradio-sequence-editor
Requires-Dist: gradio-uni-view-ocl
Requires-Dist: gradio-brm-file >=0.1.4
Requires-Dist: gradio-brm-save >=0.1.1
Requires-Dist: dp-launching-app ==0.1.0-alpha.1
